betterwinreg/__init__.py
betterwinreg/hkey.py
betterwinreg/key.py
betterwinreg/value.py
betterwinreg-1.0.0.dist-info/LICENSE
betterwinreg-1.0.0.dist-info/METADATA
betterwinreg-1.0.0.dist-info/WHEEL
betterwinreg-1.0.0.dist-info/top_level.txt
betterwinreg-1.0.0.dist-info/RECORD
