Metadata-Version: 2.1
Name: betterwinreg
Version: 1.0.0
Summary: A sane way of working with the Windows registry
Home-page: https://github.com/thefumbduck/betterwinreg
Author: thefumbduck
Author-email: 51268203+thefumbduck@users.noreply.github.com
License: GNU GPL v3
Project-URL: Bug tracker, https://github.com/thefumbduck/betterwinreg/issues
Project-URL: Documentation, https://github.com/thefumbduck/betterwinreg
Project-URL: Source code, https://github.com/thefumbduck/betterwinreg
Keywords: winreg windows registry oop
Platform: UNKNOWN
Requires-Python: >=3.7
